
{
   "type":"RestraintEvent",
   "validatorClass":"org.slc.sli.validation.ComplexSchema",
   "version":"1.0",
   "fields":{
      "*id":"ID",
      "RestraintEventIdentifier":"RestraintEventIdentifier",
      "EventDate":"date",
      "*EducationalEnvironment":"EducationalEnvironmentType",
      "RestraintEventReasons":"RestraintEventReasonsType",
      "StudentReference":"StudentReferenceType",
      "*ProgramReference":["ProgramReferenceType"],
      "SchoolReference":"EducationalOrgReferenceType"},
   "properties":{}
}
