{
    "keyFields" : ["metaData.externalId", "body.assessmentId", "body.studentId", "body.administrationDate"],
    "subEntities" : { "body.studentAssessmentItems?" : "studentAssessmentItem",
                      "body.studentObjectiveAssessments?" : "studentObjectiveAssessment"},
    "references" :
    [{
        "fieldPath" : "body.AssessmentReference",
        "deprecated" : true,
        "ref" :
        {
            "entityType" : "assessment",
            "choiceOfFields" :
            [
                [
                    {
                        "path" : "body.assessmentIdentificationCode",
                        "values" :
                        [{
                            "valueSource" : "body.AssessmentReference.AssessmentIdentity.AssessmentIdentificationCode"
                        }]
                    },
                    {
                        "path" : "body.assessmentTitle",
                        "values" :
                        [{
                            "valueSource" : "body.AssessmentReference.AssessmentIdentity.AssessmentTitle"
                        }]
                    },
                    {
                        "path" : "body.assessmentCategory",
                        "values" :
                        [{
                            "valueSource" : "body.AssessmentReference.AssessmentIdentity.AssessmentCategory"
                        }]
                    },
                    {
                        "path" : "body.academicSubject",
                        "values" :
                        [{
                            "valueSource" : "body.AssessmentReference.AssessmentIdentity.AcademicSubject"
                        }]
                    },
                    {
                        "path" : "body.gradeLevelAssessed",
                        "values" :
                        [{
                            "valueSource" : "body.AssessmentReference.AssessmentIdentity.GradeLevelAssessed"
                        }]
                    },
                    {
                        "path" : "body.version",
                        "values" :
                        [{
                            "valueSource" : "body.AssessmentReference.AssessmentIdentity.Version"
                        }]
                    }
                ]
            ]
        }
    },
    {
        "fieldPath" : "body.StudentReference",
        "deprecated" : true,
        "ref" :
        {
            "entityType" : "student",
            "choiceOfFields" :
            [
                [
                    {
                        "path" : "body.studentUniqueStateId",
                        "values" :
                        [{
                            "valueSource" : "body.StudentReference.StudentIdentity.StudentUniqueStateId"
                        }]
                    }
                ]
            ]
        }
    }]
}
